[
  {
    "github_username": "usufruct",
    "name": "Michael Anderson",
    "link_text": null,
    "link_url": null,
    "avatar_url": null,
    "bio": "I use Python at work. If Python were ordering a hot dog in Chicago it would know for certain whether ketchup is a proper condiment."
  },
  {
    "github_username": "U2328",
    "name": "Tim Fischer",
    "link_text": null,
    "link_url": null,
    "avatar_url": null,
    "bio": "I work and play with Python, some times for a living, other times just for fun."
  }
]
