[
  {
    "github_username" : "ningke",
    "name" : "Ning Ke",
    "link_text" : "GitHub profile",
    "link_url" : "https://github.com/ningke",
    "avatar_url" : null,
    "bio" : "Rediscovering the new C++."
  },
  {
    "github_username" : "nashirj",
    "name" : "Nashir Janmohamed",
    "link_text" : "Personal website",
    "link_url" : "https://www.nashirj.com",
    "avatar_url" : null,
    "bio" : "I am a CS student with experience using C++ to complete university projects and write source code for robotics platforms. I hope to share my experience and learn in the process."
  },
  {
    "github_username" : "nullpointxr",
    "name" : "Abhishek Sankar",
    "link_text" : "Reach me here!",
    "link_url" : "https://abhisheks.me",
    "avatar_url" : null,
    "bio" : "I'm a senior year CS undergrad, playing around with C++. I like tech, make memes, apps and websites in that order :)"
  }  
]
